{
    "niv": {
        "branch": "master",
        "description": "Easy dependency management for Nix projects",
        "homepage": "https://github.com/nmattia/niv",
        "owner": "nmattia",
        "repo": "niv",
        "rev": "9d35b9e4837ab88517210b1701127612c260eccf",
        "sha256": "0q50xhnm8g2yfyakrh0nly4swyygxpi0a8cb9gp65wcakcgvzvdh",
        "type": "tarball",
        "url": "https://github.com/nmattia/niv/archive/9d35b9e4837ab88517210b1701127612c260eccf.tar.gz",
        "url_template": "https://github.com/<owner>/<repo>/archive/<rev>.tar.gz"
    },
    "nix-tooling": {
        "branch": "master",
        "description": null,
        "homepage": null,
        "owner": "vladciobanu",
        "repo": "nix-tooling",
        "rev": "682582b25f1c8f94d63d3e6a332079088b0fcea2",
        "sha256": "1p79m2ydcd08qswq4ang6cx91vfx8i9hgvhd8ph25qdgl1vghydq",
        "type": "tarball",
        "url": "https://github.com/vladciobanu/nix-tooling/archive/682582b25f1c8f94d63d3e6a332079088b0fcea2.tar.gz",
        "url_template": "https://github.com/<owner>/<repo>/archive/<rev>.tar.gz"
    },
    "nixpkgs": {
        "branch": "release-20.03",
        "description": "Nix Packages collection",
        "homepage": null,
        "owner": "NixOS",
        "repo": "nixpkgs",
        "rev": "9ab537f115e1705d39b8b9ed320af374fc0a1eac",
        "sha256": "12vv6wq1cxmf9nrrlj8ix2286zw9ykhr9mljsz8v9i7z844s33zf",
        "type": "tarball",
        "url": "https://github.com/NixOS/nixpkgs/archive/9ab537f115e1705d39b8b9ed320af374fc0a1eac.tar.gz",
        "url_template": "https://github.com/<owner>/<repo>/archive/<rev>.tar.gz"
    }
}
